{
  "_class": "shapePath",
  "booleanOperation": -1,
  "do_objectID": "746D7E95-15CF-49D5-9A0D-FDC31B5B95E6",
  "edited": true,
  "exportOptions": {
    "_class": "exportOptions",
    "exportFormats": [
    ],
    "includedLayerIds": [
    ],
    "layerOptions": 0,
    "shouldTrim": false
  },
  "frame": {
    "_class": "rect",
    "constrainProportions": false,
    "height": 19,
    "width": 18,
    "x": 0,
    "y": 0
  },
  "isFlippedHorizontal": false,
  "isFlippedVertical": false,
  "isLocked": false,
  "isVisible": true,
  "layerListExpandedType": 0,
  "name": "Path",
  "nameIsFixed": false,
  "path": {
    "_class": "path",
    "isClosed": false,
    "pointRadiusBehaviour": 0,
    "points": [
      {
        "_class": "curvePoint",
        "cornerRadius": 0,
        "curveFrom": "{0.22388888888888894, 0}",
        "curveMode": 4,
        "curveTo": "{0.5, 0}",
        "hasCurveFrom": true,
        "hasCurveTo": false,
        "point": "{0.5, 0}"
      },
      {
        "_class": "curvePoint",
        "cornerRadius": 0,
        "curveFrom": "{0, 0.47368421052631576}",
        "curveMode": 4,
        "curveTo": "{0, 0.2121052631578933}",
        "hasCurveFrom": false,
        "hasCurveTo": true,
        "point": "{0, 0.47368421052631576}"
      },
      {
        "_class": "curvePoint",
        "cornerRadius": 0,
        "curveFrom": "{0, 0.92947368421052468}",
        "curveMode": 4,
        "curveTo": "{0, 0.84210526315789469}",
        "hasCurveFrom": true,
        "hasCurveTo": false,
        "point": "{0, 0.84210526315789469}"
      },
      {
        "_class": "curvePoint",
        "cornerRadius": 0,
        "curveFrom": "{0.16666666666666666, 1}",
        "curveMode": 4,
        "curveTo": "{0.074444444444444632, 1}",
        "hasCurveFrom": false,
        "hasCurveTo": true,
        "point": "{0.16666666666666666, 1}"
      },
      {
        "_class": "curvePoint",
        "cornerRadius": 0,
        "curveFrom": "{0.33333333333333331, 1}",
        "curveMode": 1,
        "curveTo": "{0.33333333333333331, 1}",
        "hasCurveFrom": false,
        "hasCurveTo": false,
        "point": "{0.33333333333333331, 1}"
      },
      {
        "_class": "curvePoint",
        "cornerRadius": 0,
        "curveFrom": "{0.33333333333333331, 0.57894736842105265}",
        "curveMode": 1,
        "curveTo": "{0.33333333333333331, 0.57894736842105265}",
        "hasCurveFrom": false,
        "hasCurveTo": false,
        "point": "{0.33333333333333331, 0.57894736842105265}"
      },
      {
        "_class": "curvePoint",
        "cornerRadius": 0,
        "curveFrom": "{0.1111111111111111, 0.57894736842105265}",
        "curveMode": 1,
        "curveTo": "{0.1111111111111111, 0.57894736842105265}",
        "hasCurveFrom": false,
        "hasCurveTo": false,
        "point": "{0.1111111111111111, 0.57894736842105265}"
      },
      {
        "_class": "curvePoint",
        "cornerRadius": 0,
        "curveFrom": "{0.1111111111111111, 0.26999999999999974}",
        "curveMode": 4,
        "curveTo": "{0.1111111111111111, 0.47368421052631576}",
        "hasCurveFrom": true,
        "hasCurveTo": false,
        "point": "{0.1111111111111111, 0.47368421052631576}"
      },
      {
        "_class": "curvePoint",
        "cornerRadius": 0,
        "curveFrom": "{0.7150000000000003, 0.10526315789473684}",
        "curveMode": 2,
        "curveTo": "{0.28499999999999975, 0.10526315789473684}",
        "hasCurveFrom": true,
        "hasCurveTo": true,
        "point": "{0.5, 0.10526315789473684}"
      },
      {
        "_class": "curvePoint",
        "cornerRadius": 0,
        "curveFrom": "{0.88888888888888884, 0.47368421052631576}",
        "curveMode": 4,
        "curveTo": "{0.88888888888888884, 0.26999999999999974}",
        "hasCurveFrom": false,
        "hasCurveTo": true,
        "point": "{0.88888888888888884, 0.47368421052631576}"
      },
      {
        "_class": "curvePoint",
        "cornerRadius": 0,
        "curveFrom": "{0.88888888888888884, 0.57894736842105265}",
        "curveMode": 1,
        "curveTo": "{0.88888888888888884, 0.57894736842105265}",
        "hasCurveFrom": false,
        "hasCurveTo": false,
        "point": "{0.88888888888888884, 0.57894736842105265}"
      },
      {
        "_class": "curvePoint",
        "cornerRadius": 0,
        "curveFrom": "{0.66666666666666663, 0.57894736842105265}",
        "curveMode": 1,
        "curveTo": "{0.66666666666666663, 0.57894736842105265}",
        "hasCurveFrom": false,
        "hasCurveTo": false,
        "point": "{0.66666666666666663, 0.57894736842105265}"
      },
      {
        "_class": "curvePoint",
        "cornerRadius": 0,
        "curveFrom": "{0.66666666666666663, 1}",
        "curveMode": 1,
        "curveTo": "{0.66666666666666663, 1}",
        "hasCurveFrom": false,
        "hasCurveTo": false,
        "point": "{0.66666666666666663, 1}"
      },
      {
        "_class": "curvePoint",
        "cornerRadius": 0,
        "curveFrom": "{0.92555555555555535, 1}",
        "curveMode": 4,
        "curveTo": "{0.83333333333333337, 1}",
        "hasCurveFrom": true,
        "hasCurveTo": false,
        "point": "{0.83333333333333337, 1}"
      },
      {
        "_class": "curvePoint",
        "cornerRadius": 0,
        "curveFrom": "{1, 0.84210526315789469}",
        "curveMode": 4,
        "curveTo": "{1, 0.92947368421052468}",
        "hasCurveFrom": false,
        "hasCurveTo": true,
        "point": "{1, 0.84210526315789469}"
      },
      {
        "_class": "curvePoint",
        "cornerRadius": 0,
        "curveFrom": "{1, 0.2121052631578933}",
        "curveMode": 4,
        "curveTo": "{1, 0.47368421052631576}",
        "hasCurveFrom": true,
        "hasCurveTo": false,
        "point": "{1, 0.47368421052631576}"
      },
      {
        "_class": "curvePoint",
        "cornerRadius": 0,
        "curveFrom": "{0.5, 0}",
        "curveMode": 4,
        "curveTo": "{0.77611111111111108, 0}",
        "hasCurveFrom": false,
        "hasCurveTo": true,
        "point": "{0.5, 0}"
      }
    ]
  },
  "resizingConstraint": 63,
  "resizingType": 0,
  "rotation": 0,
  "shouldBreakMaskChain": false
}