{
  "_class": "shapePath",
  "booleanOperation": 0,
  "do_objectID": "56F683C0-29CA-4ECE-9C1B-D49CB245D770",
  "edited": true,
  "exportOptions": {
    "_class": "exportOptions",
    "exportFormats": [
    ],
    "includedLayerIds": [
    ],
    "layerOptions": 0,
    "shouldTrim": false
  },
  "frame": {
    "_class": "rect",
    "constrainProportions": false,
    "height": 14.4712747574673,
    "width": 18.65799365881236,
    "x": 0.673314038052804,
    "y": 0.6681236872308091
  },
  "isFlippedHorizontal": false,
  "isFlippedVertical": false,
  "isLocked": false,
  "isVisible": true,
  "layerListExpandedType": 0,
  "name": "Fill 1",
  "nameIsFixed": false,
  "path": {
    "_class": "path",
    "isClosed": true,
    "pointRadiusBehaviour": 1,
    "points": [
      {
        "_class": "curvePoint",
        "cornerRadius": 0,
        "curveFrom": "{0, 1}",
        "curveMode": 1,
        "curveTo": "{0, 1}",
        "hasCurveFrom": false,
        "hasCurveTo": false,
        "point": "{0, 1}"
      },
      {
        "_class": "curvePoint",
        "cornerRadius": 0,
        "curveFrom": "{1, 1}",
        "curveMode": 1,
        "curveTo": "{1, 1}",
        "hasCurveFrom": false,
        "hasCurveTo": false,
        "point": "{1, 1}"
      },
      {
        "_class": "curvePoint",
        "cornerRadius": 0,
        "curveFrom": "{1, 0.49536345776031437}",
        "curveMode": 1,
        "curveTo": "{1, 0.49536345776031437}",
        "hasCurveFrom": false,
        "hasCurveTo": false,
        "point": "{1, 0.49536345776031437}"
      },
      {
        "_class": "curvePoint",
        "cornerRadius": 0,
        "curveFrom": "{0.82772072044616463, 0}",
        "curveMode": 1,
        "curveTo": "{0.82772072044616463, 0}",
        "hasCurveFrom": false,
        "hasCurveTo": false,
        "point": "{0.82772072044616463, 0}"
      },
      {
        "_class": "curvePoint",
        "cornerRadius": 0,
        "curveFrom": "{0.17224880382775118, 0}",
        "curveMode": 1,
        "curveTo": "{0.17224880382775118, 0}",
        "hasCurveFrom": false,
        "hasCurveTo": false,
        "point": "{0.17224880382775118, 0}"
      },
      {
        "_class": "curvePoint",
        "cornerRadius": 0,
        "curveFrom": "{0, 0.4928880157170924}",
        "curveMode": 1,
        "curveTo": "{0, 0.4928880157170924}",
        "hasCurveFrom": false,
        "hasCurveTo": false,
        "point": "{0, 0.4928880157170924}"
      }
    ]
  },
  "resizingConstraint": 63,
  "resizingType": 0,
  "rotation": 0,
  "shouldBreakMaskChain": false
}