{
  "_class": "group",
  "do_objectID": "91286CCA-44E7-4F9B-9BFB-31CE6CD49A3E",
  "exportOptions": {
    "_class": "exportOptions",
    "exportFormats": [
    ],
    "includedLayerIds": [
    ],
    "layerOptions": 0,
    "shouldTrim": false
  },
  "frame": {
    "_class": "rect",
    "constrainProportions": false,
    "height": 57,
    "width": 56,
    "x": 235,
    "y": 11
  },
  "hasClickThrough": false,
  "isFlippedHorizontal": false,
  "isFlippedVertical": false,
  "isLocked": false,
  "isVisible": true,
  "layerListExpandedType": 0,
  "layers": [
    {
      "class": "text",
      "id": "32C9B9AA-52D6-4434-A6B1-BF50C7E0A1C4"
    },
    {
      "class": "text",
      "id": "09D158CB-7C41-4C46-83FE-79CB6AE1B560"
    },
    {
      "class": "group",
      "id": "B5C929DF-5F38-44EE-ACE6-70FC97143DBC"
    }
  ],
  "name": "Group",
  "nameIsFixed": false,
  "resizingConstraint": 63,
  "resizingType": 0,
  "rotation": 0,
  "shouldBreakMaskChain": false,
  "style": {
    "_class": "style",
    "blur": {
      "_class": "blur",
      "center": "{0.5, 0.5}",
      "isEnabled": false,
      "motionAngle": 0,
      "radius": 2.036363636363637,
      "type": 0
    },
    "endDecorationType": 0,
    "miterLimit": 10,
    "startDecorationType": 0
  }
}